data_tree/__init__.py
data_tree/_series.py
data_tree/cache.py
data_tree/checks.py
data_tree/coconut/__coconut__.py
data_tree/coconut/__init__.py
data_tree/coconut/calc.py
data_tree/coconut/controllable.py
data_tree/coconut/ops/__init__.py
data_tree/coconut/ops/control.py
data_tree/coconut/rules/__init__.py
data_tree/coconut/smart.py
data_tree/colorconv.py
data_tree/config.py
data_tree/custom_resource.py
data_tree/custom_zmq.py
data_tree/disk_cache.py
data_tree/dt_ast/__init__.py
data_tree/dt_ast/dt_core.py
data_tree/dt_ast/free_monad.py
data_tree/dt_ast/injected_wrapper.py
data_tree/dt_ast/node.py
data_tree/dt_wandb/__init__.py
data_tree/dt_wandb/json_artifact.py
data_tree/dt_wandb/wandb_util.py
data_tree/dtype.py
data_tree/format_converter.py
data_tree/get_callee.py
data_tree/image_store.py
data_tree/image_store_creator.py
data_tree/image_store_pkg/__init__.py
data_tree/image_store_pkg/converter.py
data_tree/image_store_pkg/lmdb.py
data_tree/image_store_pkg/test_lmdb.py
data_tree/indexer.py
data_tree/key_value_cache.py
data_tree/key_value_store.py
data_tree/kvc_errors.py
data_tree/lmdb_bytes_kvs.py
data_tree/lmdb_helper.py
data_tree/lmdb_util.py
data_tree/mlmdb_kvs.py
data_tree/mocks/__init__.py
data_tree/mocks/images.py
data_tree/monad/core.py
data_tree/monad/try_monad.py
data_tree/mp_util.py
data_tree/ops/__init__.py
data_tree/ops/cache.py
data_tree/periodic.py
data_tree/picklable_file_lock.py
data_tree/pipe.py
data_tree/serialization_protocol.py
data_tree/series_util/__init__.py
data_tree/sftp_util.py
data_tree/storage_manager.py
data_tree/table.py
data_tree/test/coconut/__coconut__.py
data_tree/test/coconut/__init__.py
data_tree/test/coconut/test_conversion.py
data_tree/test/coconut/test_mp_queue.py
data_tree/test_key_value_store.py
data_tree/test_util.py
data_tree/timed_cache.py
data_tree/util.py
data_tree/visdom.py
data_tree/visualization.py
data_tree/wandb_util/__init__.py
data_tree/wandb_util/artifact.py
data_tree/wandb_util/artifact_cache.py
proboscis_data_tree-0.1.2.dist-info/METADATA
proboscis_data_tree-0.1.2.dist-info/WHEEL
proboscis_data_tree-0.1.2.dist-info/RECORD
